kg_detective/__init__.py
kg_detective/constants.py
kg_detective/de/__init__.py
kg_detective/de/kg_fn.py
kg_detective/de/kg_translation.py
kg_detective/de/rules/__init__.py
kg_detective/de/rules/adj_deklination.py
kg_detective/de/rules/adj_ergänzung_mit_präposition.py
kg_detective/de/rules/adj_komparativ.py
kg_detective/de/rules/adj_norminalisierte.py
kg_detective/de/rules/adj_ohne_steigerung.py
kg_detective/de/rules/adj_superlativ.py
kg_detective/de/rules/adv_grad.py
kg_detective/de/rules/adv_kasual.py
kg_detective/de/rules/adv_komparation.py
kg_detective/de/rules/adv_lokal.py
kg_detective/de/rules/adv_modal.py
kg_detective/de/rules/adv_temporal.py
kg_detective/de/rules/art_bestimmer.py
kg_detective/de/rules/art_demostrativ.py
kg_detective/de/rules/art_null.py
kg_detective/de/rules/art_possessiv.py
kg_detective/de/rules/art_unbestimmer.py
kg_detective/de/rules/conj_einfache.py
kg_detective/de/rules/conj_zweiteilige.py
kg_detective/de/rules/frag_frag.py
kg_detective/de/rules/noun_genus.py
kg_detective/de/rules/noun_kasus.py
kg_detective/de/rules/noun_pluralform.py
kg_detective/de/rules/prep_mit_akkusativ.py
kg_detective/de/rules/prep_mit_akkusativ_order_dativ.py
kg_detective/de/rules/prep_mit_dativ.py
kg_detective/de/rules/prep_mit_genitiv.py
kg_detective/de/rules/prep_temporale.py
kg_detective/de/rules/pron_demostrativ.py
kg_detective/de/rules/pron_indefinit.py
kg_detective/de/rules/pron_personal.py
kg_detective/de/rules/pron_possessiv.py
kg_detective/de/rules/pron_reflexiv.py
kg_detective/de/rules/pron_relativ.py
kg_detective/de/rules/satz_adverbial.py
kg_detective/de/rules/satz_objekt.py
kg_detective/de/rules/satz_prädikativ.py
kg_detective/de/rules/satz_relativ.py
kg_detective/de/rules/satz_subjekt.py
kg_detective/de/rules/verb_ergänzungen_im_akkusativ.py
kg_detective/de/rules/verb_ergänzungen_im_akkusativ_akkusativ.py
kg_detective/de/rules/verb_ergänzungen_im_dativ.py
kg_detective/de/rules/verb_ergänzungen_im_dativ_akkusativ.py
kg_detective-0.1.29.dist-info/METADATA
kg_detective-0.1.29.dist-info/WHEEL
kg_detective-0.1.29.dist-info/RECORD
