Metadata-Version: 2.3
Name: kg-detective
Version: 0.1.29
Summary: Knowledge Graph recognizer component for spacy pipeline
Author: Phoenix Grey
Author-email: phoenix.grey0108@gmail.com
Requires-Python: >=3.12,<4.0
Classifier: Programming Language :: Python :: 3
Classifier: Programming Language :: Python :: 3.12
Classifier: Programming Language :: Python :: 3.13
Requires-Dist: spacy (==3.7.5)
